pytekswift-0.1.7.dist-info/licenses/LICENSE
tekswift/__init__.py
tekswift/cli.py
tekswift/dataloader.py
tekswift/utils.py
tekswift/data/__init__.py
tekswift/data/ad.yml
tekswift/data/ae.yml
tekswift/data/af.yml
tekswift/data/ag.yml
tekswift/data/ai.yml
tekswift/data/al.yml
tekswift/data/am.yml
tekswift/data/ao.yml
tekswift/data/ar.yml
tekswift/data/as.yml
tekswift/data/at.yml
tekswift/data/au.yml
tekswift/data/aw.yml
tekswift/data/az.yml
tekswift/data/ba.yml
tekswift/data/bb.yml
tekswift/data/bd.yml
tekswift/data/be.yml
tekswift/data/bf.yml
tekswift/data/bg.yml
tekswift/data/bh.yml
tekswift/data/bi.yml
tekswift/data/bj.yml
tekswift/data/bm.yml
tekswift/data/bn.yml
tekswift/data/bo.yml
tekswift/data/bq.yml
tekswift/data/br.yml
tekswift/data/bs.yml
tekswift/data/bt.yml
tekswift/data/bw.yml
tekswift/data/by.yml
tekswift/data/bz.yml
tekswift/data/ca.yml
tekswift/data/cd.yml
tekswift/data/cf.yml
tekswift/data/cg.yml
tekswift/data/ch.yml
tekswift/data/ci.yml
tekswift/data/ck.yml
tekswift/data/cl.yml
tekswift/data/cm.yml
tekswift/data/cn.yml
tekswift/data/co.yml
tekswift/data/cr.yml
tekswift/data/cu.yml
tekswift/data/cv.yml
tekswift/data/cw.yml
tekswift/data/cy.yml
tekswift/data/cz.yml
tekswift/data/de.yml
tekswift/data/dj.yml
tekswift/data/dk.yml
tekswift/data/dm.yml
tekswift/data/do.yml
tekswift/data/dz.yml
tekswift/data/ec.yml
tekswift/data/ee.yml
tekswift/data/eg.yml
tekswift/data/er.yml
tekswift/data/es.yml
tekswift/data/et.yml
tekswift/data/fi.yml
tekswift/data/fj.yml
tekswift/data/fk.yml
tekswift/data/fm.yml
tekswift/data/fo.yml
tekswift/data/fr.yml
tekswift/data/ga.yml
tekswift/data/gb.yml
tekswift/data/gd.yml
tekswift/data/ge.yml
tekswift/data/gf.yml
tekswift/data/gg.yml
tekswift/data/gh.yml
tekswift/data/gi.yml
tekswift/data/gl.yml
tekswift/data/gm.yml
tekswift/data/gn.yml
tekswift/data/gp.yml
tekswift/data/gq.yml
tekswift/data/gr.yml
tekswift/data/gt.yml
tekswift/data/gu.yml
tekswift/data/gw.yml
tekswift/data/gy.yml
tekswift/data/hk.yml
tekswift/data/hn.yml
tekswift/data/hr.yml
tekswift/data/ht.yml
pytekswift-0.1.7.dist-info/METADATA
pytekswift-0.1.7.dist-info/WHEEL
pytekswift-0.1.7.dist-info/entry_points.txt
pytekswift-0.1.7.dist-info/top_level.txt
pytekswift-0.1.7.dist-info/RECORD
