Metadata-Version: 2.4
Name: pytekswift
Version: 0.1.7
Summary: "Database and Utilities for SWIFT (The Society for Worldwide Interbank Financial Telecommunication), a network that enables financial institutions worldwide to send and receive information about financial transactions in a secure, standardized and reliable environment."
Home-page: https://github.com/TralahM/pytekswift
Author: Tralah M Brian
Author-email: musyoki.brian@tralahtek.com
License: GPLV3
Project-URL: source, https://github.com/TralahM/pytekswift/
Project-URL: tracker, https://github.com/TralahM/pytekswift/issues
Keywords: "development credit_cards database finance"
Classifier: Development Status :: 4 - Beta
Classifier: Intended Audience :: Developers
Classifier: Topic :: Software Development :: Build Tools
Classifier: Topic :: Database
Classifier: Topic :: Software Development :: Libraries
Classifier: Topic :: System :: Shells
Classifier: Topic :: Utilities
Classifier: License :: OSI Approved :: GNU General Public License v3 (GPLv3)
Classifier: Natural Language :: English
Classifier: Programming Language :: Python :: 3
Classifier: Programming Language :: Python :: 3.2
Classifier: Programming Language :: Python :: 3.3
Classifier: Programming Language :: Python :: 3.4
Classifier: Programming Language :: Python :: 3.5
Classifier: Programming Language :: Python :: 3.6
Classifier: Programming Language :: Python :: 3.7
Classifier: Programming Language :: Python :: 3.8
Classifier: Programming Language :: Python :: 3.9
Classifier: Operating System :: Unix
License-File: LICENSE
Requires-Dist: PyYaml
Requires-Dist: nltk
Requires-Dist: shtab
Requires-Dist: pycctek
Requires-Dist: fuzzywuzzy
Requires-Dist: scikit-learn
Dynamic: license-file
